easysock/.DS_Store
easysock/__init__.py
easysock/main.py
easysock-1.0.0.dist-info/LICENSE
easysock-1.0.0.dist-info/WHEEL
easysock-1.0.0.dist-info/METADATA
easysock-1.0.0.dist-info/RECORD
