Metadata-Version: 1.2
Name: easysock
Version: 1.0.0
Summary: Easysock is a easy socket interface
Home-page: https://easysocket.wordpress.com
License: UNKNOWN
Author: Raleigh Wise
Author-email: none@none.com
Classifier: License :: OSI Approved :: MIT License
